_cds.cpython-311-aarch64-linux-gnu.so
pycds.pth
cds/dump.py
cds/_cds.pyi
cds/__init__.py
code_data_share-0.1.0.dist-info/METADATA
code_data_share-0.1.0.dist-info/RECORD
code_data_share-0.1.0.dist-info/entry_points.txt
code_data_share-0.1.0.dist-info/WHEEL
code_data_share-0.1.0.dist-info/licenses/LICENSE
